{
  "metadata": {
    "siteNumber": "0457",
    "customerName": "Providence Alaska Medical Center",
    "customerID": "CUST-0457",
    "contractEffectiveDate": "2025-05-23",
    "contractEndDate": "",
    "contractStatus": "active",
    "lastModifiedDate": "2025-05-23",
    "contractVersion": "1.0",
    "contractType": "Fixed Fee; Invoice Grouping",
    "accountManager": "Frederick Little",
    "paymentTerms": "Due in 30 Days",
    "notes": NaN,
    "location": {
      "region": NaN,
      "district": "D - Portland",
      "state": "AK",
      "city": "Anchorage",
      "address": "3200 Providence Drive, Anchorage, AK 99508",
      "siteType": ""
    }
  },
  "original": {
    "id": "b14f02e4-90d8-ef11-8eea-0022480a57ac",
    "purchaseOrder": null,
    "paymentTerms": "Due in 30 Days",
    "billingType": "Advanced",
    "incrementMonth": "January",
    "incrementAmount": 0.0,
    "consumerPriceIndex": false,
    "notes": null,
    "deviationAmount": 2500.0,
    "deviationPercentage": 10.0,
    "deposits": false,
    "contractType": "Fixed Fee",
    "supportingReports": [],
    "invoiceGrouping": {
      "enabled": true,
      "invoiceGroups": [
        {
          "id": "20f3f4b6-b7e0-ef11-a730-002248251de6",
          "groupNumber": 1,
          "title": "Valet Services",
          "description": "Purchase Order: P0010000934644",
          "vendorId": null,
          "siteNumber": "0457",
          "customerName": "PAMC Main Campus Valet Services",
          "billingContactEmails": "valerie.tobin@providence.org;providence@ghxinvoicing.com"
        },
        {
          "id": "24f3f4b6-b7e0-ef11-a730-002248251de6",
          "groupNumber": 2,
          "title": "Valet Services - S, T and U Towers",
          "description": "Purchase Order: P0010000982488",
          "vendorId": null,
          "siteNumber": "0457",
          "customerName": "Providence Alaska Medical Center - S, T and U Towers",
          "billingContactEmails": "ariele.meinhardt@providence.org;providence@ghxinvoicing.com"
        }
      ]
    },
    "fixedFee": {
      "enabled": true,
      "serviceRates": [
        {
          "id": "1df3f4b6-b7e0-ef11-a730-002248251de6",
          "name": "Valet Services",
          "displayName": "Valet Services",
          "code": "4700",
          "fee": 10475.98,
          "startDate": "2025-01-22T09:42:57",
          "endDate": null,
          "invoiceGroup": 1
        },
        {
          "id": "1ff3f4b6-b7e0-ef11-a730-002248251de6",
          "name": "Valet Services",
          "displayName": "Valet Services S, T and U Towers",
          "code": "4700",
          "fee": 19455.24,
          "startDate": "2025-01-22T09:42:57",
          "endDate": null,
          "invoiceGroup": 2
        }
      ]
    },
    "perLaborHour": {
      "enabled": false,
      "hoursBackupReport": false,
      "jobRates": []
    },
    "perOccupiedRoom": {
      "enabled": false,
      "roomRate": 0.0,
      "invoiceGroup": 1
    },
    "revenueShare": {
      "enabled": false,
      "thresholdStructures": []
    },
    "bellServiceFee": {
      "enabled": false,
      "bellServices": []
    },
    "midMonthAdvance": {
      "enabled": false,
      "midMonthAdvances": []
    },
    "depositedRevenue": {
      "enabled": false,
      "depositData": []
    },
    "billableAccounts": {
      "enabled": false,
      "billableAccountsData": []
    },
    "managementAgreement": {
      "enabled": false,
      "ManagementFees": []
    }
  },
  "flattened": {
    "contract_id": "b14f02e4-90d8-ef11-8eea-0022480a57ac",
    "contract_purchaseOrder": null,
    "contract_paymentTerms": "Due in 30 Days",
    "contract_billingType": "Advanced",
    "contract_incrementMonth": "January",
    "contract_incrementAmount": 0.0,
    "contract_consumerPriceIndex": false,
    "contract_notes": null,
    "contract_deviationAmount": 2500.0,
    "contract_deviationPercentage": 10.0,
    "contract_deposits": false,
    "contract_contractType": "Fixed Fee",
    "contract_invoiceGrouping_enabled": true,
    "contract_invoiceGrouping_invoiceGroups_1_id": "20f3f4b6-b7e0-ef11-a730-002248251de6",
    "contract_invoiceGrouping_invoiceGroups_1_groupNumber": 1,
    "contract_invoiceGrouping_invoiceGroups_1_title": "Valet Services",
    "contract_invoiceGrouping_invoiceGroups_1_description": "Purchase Order: P0010000934644",
    "contract_invoiceGrouping_invoiceGroups_1_vendorId": null,
    "contract_invoiceGrouping_invoiceGroups_1_siteNumber": "0457",
    "contract_invoiceGrouping_invoiceGroups_1_customerName": "PAMC Main Campus Valet Services",
    "contract_invoiceGrouping_invoiceGroups_1_billingContactEmails": "valerie.tobin@providence.org;providence@ghxinvoicing.com",
    "contract_invoiceGrouping_invoiceGroups_2_id": "24f3f4b6-b7e0-ef11-a730-002248251de6",
    "contract_invoiceGrouping_invoiceGroups_2_groupNumber": 2,
    "contract_invoiceGrouping_invoiceGroups_2_title": "Valet Services - S, T and U Towers",
    "contract_invoiceGrouping_invoiceGroups_2_description": "Purchase Order: P0010000982488",
    "contract_invoiceGrouping_invoiceGroups_2_vendorId": null,
    "contract_invoiceGrouping_invoiceGroups_2_siteNumber": "0457",
    "contract_invoiceGrouping_invoiceGroups_2_customerName": "Providence Alaska Medical Center - S, T and U Towers",
    "contract_invoiceGrouping_invoiceGroups_2_billingContactEmails": "ariele.meinhardt@providence.org;providence@ghxinvoicing.com",
    "contract_fixedFee_enabled": true,
    "contract_fixedFee_serviceRates_1_id": "1df3f4b6-b7e0-ef11-a730-002248251de6",
    "contract_fixedFee_serviceRates_1_name": "Valet Services",
    "contract_fixedFee_serviceRates_1_displayName": "Valet Services",
    "contract_fixedFee_serviceRates_1_code": "4700",
    "contract_fixedFee_serviceRates_1_fee": 10475.98,
    "contract_fixedFee_serviceRates_1_startDate": "2025-01-22T09:42:57",
    "contract_fixedFee_serviceRates_1_endDate": null,
    "contract_fixedFee_serviceRates_1_invoiceGroup": 1,
    "contract_fixedFee_serviceRates_2_id": "1ff3f4b6-b7e0-ef11-a730-002248251de6",
    "contract_fixedFee_serviceRates_2_name": "Valet Services",
    "contract_fixedFee_serviceRates_2_displayName": "Valet Services S, T and U Towers",
    "contract_fixedFee_serviceRates_2_code": "4700",
    "contract_fixedFee_serviceRates_2_fee": 19455.24,
    "contract_fixedFee_serviceRates_2_startDate": "2025-01-22T09:42:57",
    "contract_fixedFee_serviceRates_2_endDate": null,
    "contract_fixedFee_serviceRates_2_invoiceGroup": 2,
    "contract_perLaborHour_enabled": false,
    "contract_perLaborHour_hoursBackupReport": false,
    "contract_perOccupiedRoom_enabled": false,
    "contract_perOccupiedRoom_roomRate": 0.0,
    "contract_perOccupiedRoom_invoiceGroup": 1,
    "contract_revenueShare_enabled": false,
    "contract_bellServiceFee_enabled": false,
    "contract_midMonthAdvance_enabled": false,
    "contract_depositedRevenue_enabled": false,
    "contract_billableAccounts_enabled": false,
    "contract_managementAgreement_enabled": false,
    "contract_enabled_components": [
      "fixedFee"
    ],
    "contract_payroll_accounts_enabled": [],
    "contract_expense_accounts_enabled": [],
    "contract_financials": {
      "annualContractValue": 0.0,
      "estimatedMonthlyRevenue": 0.0,
      "contractTerm": 36,
      "contractTermUnit": "Months",
      "contractType": "Fixed Fee; Invoice Grouping",
      "billingType": "Advanced",
      "district": "D - Portland",
      "region": NaN,
      "siteNumber": "0457"
    }
  }
}