{
  "metadata": {
    "siteNumber": "2172",
    "customerName": "Mass Eye and Ear",
    "customerID": "CUST-2172",
    "contractEffectiveDate": "2025-05-23",
    "contractEndDate": "",
    "contractStatus": "active",
    "lastModifiedDate": "2025-05-23",
    "contractVersion": "1.0",
    "contractType": "Per Labor Hour; Mid Month Advance; Deposited Revenue",
    "accountManager": "Timothy Desilets",
    "paymentTerms": "Due in 45 Days",
    "notes": NaN,
    "location": {
      "region": NaN,
      "district": "D - Boston",
      "state": "MA",
      "city": "Boston",
      "address": "243 Charles St., Boston, MA 2114",
      "siteType": ""
    }
  },
  "original": {
    "id": "58234fe2-92d8-ef11-8eea-0022480a57ac",
    "purchaseOrder": "PO-10027028",
    "paymentTerms": "Due in 45 Days",
    "billingType": "Arrears",
    "incrementMonth": "January",
    "incrementAmount": 2.0,
    "consumerPriceIndex": false,
    "notes": null,
    "deviationAmount": 2500.0,
    "deviationPercentage": 10.0,
    "deposits": true,
    "contractType": "Per Labor Hour",
    "supportingReports": [],
    "invoiceGrouping": {
      "enabled": false,
      "invoiceGroups": []
    },
    "fixedFee": {
      "enabled": false,
      "serviceRates": []
    },
    "perLaborHour": {
      "enabled": true,
      "hoursBackupReport": true,
      "jobRates": [
        {
          "id": "35f9c3f4-b7e0-ef11-a731-7c1e527e6e28",
          "name": "Valet Services",
          "displayName": "Cashier",
          "rate": 26.34,
          "overtimeRate": 26.34,
          "jobCode": "CASH",
          "startDate": null,
          "endDate": null,
          "invoiceGroup": 1
        },
        {
          "id": "36f9c3f4-b7e0-ef11-a731-7c1e527e6e28",
          "name": "Valet Services",
          "displayName": "Greeter",
          "rate": 26.34,
          "overtimeRate": 26.34,
          "jobCode": "GREETER",
          "startDate": null,
          "endDate": null,
          "invoiceGroup": 1
        },
        {
          "id": "37f9c3f4-b7e0-ef11-a731-7c1e527e6e28",
          "name": "Valet Services",
          "displayName": "GSA",
          "rate": 25.57,
          "overtimeRate": 25.57,
          "jobCode": "GSA",
          "startDate": null,
          "endDate": null,
          "invoiceGroup": 1
        },
        {
          "id": "38f9c3f4-b7e0-ef11-a731-7c1e527e6e28",
          "name": "Valet Services",
          "displayName": "GSC",
          "rate": 29.8,
          "overtimeRate": 29.8,
          "jobCode": "GSC",
          "startDate": null,
          "endDate": null,
          "invoiceGroup": 1
        },
        {
          "id": "39f9c3f4-b7e0-ef11-a731-7c1e527e6e28",
          "name": "Valet Services",
          "displayName": "Lot Monitor",
          "rate": 26.34,
          "overtimeRate": 26.34,
          "jobCode": "LOTATTND",
          "startDate": null,
          "endDate": null,
          "invoiceGroup": 1
        },
        {
          "id": "3af9c3f4-b7e0-ef11-a731-7c1e527e6e28",
          "name": "Valet Services",
          "displayName": "Porter",
          "rate": 26.34,
          "overtimeRate": 26.34,
          "jobCode": "PORTER",
          "startDate": null,
          "endDate": null,
          "invoiceGroup": 1
        },
        {
          "id": "3bf9c3f4-b7e0-ef11-a731-7c1e527e6e28",
          "name": "Valet Services",
          "displayName": "Account Manager",
          "rate": 44.22,
          "overtimeRate": 44.22,
          "jobCode": "ACCTMGR",
          "startDate": null,
          "endDate": null,
          "invoiceGroup": 1
        },
        {
          "id": "3cf9c3f4-b7e0-ef11-a731-7c1e527e6e28",
          "name": "Valet Services",
          "displayName": "Director of Operations",
          "rate": 47.54,
          "overtimeRate": 47.54,
          "jobCode": "DOO",
          "startDate": null,
          "endDate": null,
          "invoiceGroup": 1
        },
        {
          "id": "3df9c3f4-b7e0-ef11-a731-7c1e527e6e28",
          "name": "Valet Services",
          "displayName": "Associate Account Manager",
          "rate": 44.22,
          "overtimeRate": 44.22,
          "jobCode": "ASSOCM",
          "startDate": null,
          "endDate": null,
          "invoiceGroup": 1
        }
      ]
    },
    "perOccupiedRoom": {
      "enabled": false,
      "roomRate": 0.0,
      "invoiceGroup": 1
    },
    "revenueShare": {
      "enabled": false,
      "thresholdStructures": []
    },
    "bellServiceFee": {
      "enabled": false,
      "bellServices": []
    },
    "midMonthAdvance": {
      "enabled": true,
      "midMonthAdvances": [
        {
          "id": "33f9c3f4-b7e0-ef11-a731-7c1e527e6e28",
          "amount": 45000.0,
          "lineTitle": "MidMonthBilling",
          "invoiceGroup": 1
        }
      ]
    },
    "depositedRevenue": {
      "enabled": true,
      "depositData": [
        {
          "id": "34f9c3f4-b7e0-ef11-a731-7c1e527e6e28",
          "towneParkResponsibleForParkingTax": false,
          "depositedRevenueEnabled": true,
          "invoiceGroup": 1
        }
      ]
    },
    "billableAccounts": {
      "enabled": false,
      "billableAccountsData": []
    },
    "managementAgreement": {
      "enabled": false,
      "ManagementFees": []
    }
  },
  "flattened": {
    "contract_id": "58234fe2-92d8-ef11-8eea-0022480a57ac",
    "contract_purchaseOrder": "PO-10027028",
    "contract_paymentTerms": "Due in 45 Days",
    "contract_billingType": "Arrears",
    "contract_incrementMonth": "January",
    "contract_incrementAmount": 2.0,
    "contract_consumerPriceIndex": false,
    "contract_notes": null,
    "contract_deviationAmount": 2500.0,
    "contract_deviationPercentage": 10.0,
    "contract_deposits": true,
    "contract_contractType": "Per Labor Hour",
    "contract_invoiceGrouping_enabled": false,
    "contract_fixedFee_enabled": false,
    "contract_perLaborHour_enabled": true,
    "contract_perLaborHour_hoursBackupReport": true,
    "contract_perLaborHour_jobRates_1_id": "35f9c3f4-b7e0-ef11-a731-7c1e527e6e28",
    "contract_perLaborHour_jobRates_1_name": "Valet Services",
    "contract_perLaborHour_jobRates_1_displayName": "Cashier",
    "contract_perLaborHour_jobRates_1_rate": 26.34,
    "contract_perLaborHour_jobRates_1_overtimeRate": 26.34,
    "contract_perLaborHour_jobRates_1_jobCode": "CASH",
    "contract_perLaborHour_jobRates_1_startDate": null,
    "contract_perLaborHour_jobRates_1_endDate": null,
    "contract_perLaborHour_jobRates_1_invoiceGroup": 1,
    "contract_perLaborHour_jobRates_2_id": "36f9c3f4-b7e0-ef11-a731-7c1e527e6e28",
    "contract_perLaborHour_jobRates_2_name": "Valet Services",
    "contract_perLaborHour_jobRates_2_displayName": "Greeter",
    "contract_perLaborHour_jobRates_2_rate": 26.34,
    "contract_perLaborHour_jobRates_2_overtimeRate": 26.34,
    "contract_perLaborHour_jobRates_2_jobCode": "GREETER",
    "contract_perLaborHour_jobRates_2_startDate": null,
    "contract_perLaborHour_jobRates_2_endDate": null,
    "contract_perLaborHour_jobRates_2_invoiceGroup": 1,
    "contract_perLaborHour_jobRates_3_id": "37f9c3f4-b7e0-ef11-a731-7c1e527e6e28",
    "contract_perLaborHour_jobRates_3_name": "Valet Services",
    "contract_perLaborHour_jobRates_3_displayName": "GSA",
    "contract_perLaborHour_jobRates_3_rate": 25.57,
    "contract_perLaborHour_jobRates_3_overtimeRate": 25.57,
    "contract_perLaborHour_jobRates_3_jobCode": "GSA",
    "contract_perLaborHour_jobRates_3_startDate": null,
    "contract_perLaborHour_jobRates_3_endDate": null,
    "contract_perLaborHour_jobRates_3_invoiceGroup": 1,
    "contract_perLaborHour_jobRates_4_id": "38f9c3f4-b7e0-ef11-a731-7c1e527e6e28",
    "contract_perLaborHour_jobRates_4_name": "Valet Services",
    "contract_perLaborHour_jobRates_4_displayName": "GSC",
    "contract_perLaborHour_jobRates_4_rate": 29.8,
    "contract_perLaborHour_jobRates_4_overtimeRate": 29.8,
    "contract_perLaborHour_jobRates_4_jobCode": "GSC",
    "contract_perLaborHour_jobRates_4_startDate": null,
    "contract_perLaborHour_jobRates_4_endDate": null,
    "contract_perLaborHour_jobRates_4_invoiceGroup": 1,
    "contract_perLaborHour_jobRates_5_id": "39f9c3f4-b7e0-ef11-a731-7c1e527e6e28",
    "contract_perLaborHour_jobRates_5_name": "Valet Services",
    "contract_perLaborHour_jobRates_5_displayName": "Lot Monitor",
    "contract_perLaborHour_jobRates_5_rate": 26.34,
    "contract_perLaborHour_jobRates_5_overtimeRate": 26.34,
    "contract_perLaborHour_jobRates_5_jobCode": "LOTATTND",
    "contract_perLaborHour_jobRates_5_startDate": null,
    "contract_perLaborHour_jobRates_5_endDate": null,
    "contract_perLaborHour_jobRates_5_invoiceGroup": 1,
    "contract_perLaborHour_jobRates_6_id": "3af9c3f4-b7e0-ef11-a731-7c1e527e6e28",
    "contract_perLaborHour_jobRates_6_name": "Valet Services",
    "contract_perLaborHour_jobRates_6_displayName": "Porter",
    "contract_perLaborHour_jobRates_6_rate": 26.34,
    "contract_perLaborHour_jobRates_6_overtimeRate": 26.34,
    "contract_perLaborHour_jobRates_6_jobCode": "PORTER",
    "contract_perLaborHour_jobRates_6_startDate": null,
    "contract_perLaborHour_jobRates_6_endDate": null,
    "contract_perLaborHour_jobRates_6_invoiceGroup": 1,
    "contract_perLaborHour_jobRates_7_id": "3bf9c3f4-b7e0-ef11-a731-7c1e527e6e28",
    "contract_perLaborHour_jobRates_7_name": "Valet Services",
    "contract_perLaborHour_jobRates_7_displayName": "Account Manager",
    "contract_perLaborHour_jobRates_7_rate": 44.22,
    "contract_perLaborHour_jobRates_7_overtimeRate": 44.22,
    "contract_perLaborHour_jobRates_7_jobCode": "ACCTMGR",
    "contract_perLaborHour_jobRates_7_startDate": null,
    "contract_perLaborHour_jobRates_7_endDate": null,
    "contract_perLaborHour_jobRates_7_invoiceGroup": 1,
    "contract_perLaborHour_jobRates_8_id": "3cf9c3f4-b7e0-ef11-a731-7c1e527e6e28",
    "contract_perLaborHour_jobRates_8_name": "Valet Services",
    "contract_perLaborHour_jobRates_8_displayName": "Director of Operations",
    "contract_perLaborHour_jobRates_8_rate": 47.54,
    "contract_perLaborHour_jobRates_8_overtimeRate": 47.54,
    "contract_perLaborHour_jobRates_8_jobCode": "DOO",
    "contract_perLaborHour_jobRates_8_startDate": null,
    "contract_perLaborHour_jobRates_8_endDate": null,
    "contract_perLaborHour_jobRates_8_invoiceGroup": 1,
    "contract_perLaborHour_jobRates_9_id": "3df9c3f4-b7e0-ef11-a731-7c1e527e6e28",
    "contract_perLaborHour_jobRates_9_name": "Valet Services",
    "contract_perLaborHour_jobRates_9_displayName": "Associate Account Manager",
    "contract_perLaborHour_jobRates_9_rate": 44.22,
    "contract_perLaborHour_jobRates_9_overtimeRate": 44.22,
    "contract_perLaborHour_jobRates_9_jobCode": "ASSOCM",
    "contract_perLaborHour_jobRates_9_startDate": null,
    "contract_perLaborHour_jobRates_9_endDate": null,
    "contract_perLaborHour_jobRates_9_invoiceGroup": 1,
    "contract_perOccupiedRoom_enabled": false,
    "contract_perOccupiedRoom_roomRate": 0.0,
    "contract_perOccupiedRoom_invoiceGroup": 1,
    "contract_revenueShare_enabled": false,
    "contract_bellServiceFee_enabled": false,
    "contract_midMonthAdvance_enabled": true,
    "contract_midMonthAdvance_midMonthAdvances_1_id": "33f9c3f4-b7e0-ef11-a731-7c1e527e6e28",
    "contract_midMonthAdvance_midMonthAdvances_1_amount": 45000.0,
    "contract_midMonthAdvance_midMonthAdvances_1_lineTitle": "MidMonthBilling",
    "contract_midMonthAdvance_midMonthAdvances_1_invoiceGroup": 1,
    "contract_depositedRevenue_enabled": true,
    "contract_depositedRevenue_depositData_1_id": "34f9c3f4-b7e0-ef11-a731-7c1e527e6e28",
    "contract_depositedRevenue_depositData_1_towneParkResponsibleForParkingTax": false,
    "contract_depositedRevenue_depositData_1_depositedRevenueEnabled": true,
    "contract_depositedRevenue_depositData_1_invoiceGroup": 1,
    "contract_billableAccounts_enabled": false,
    "contract_managementAgreement_enabled": false,
    "contract_enabled_components": [
      "perLaborHour",
      "midMonthAdvance",
      "depositedRevenue"
    ],
    "contract_payroll_accounts_enabled": [],
    "contract_expense_accounts_enabled": [],
    "contract_financials": {
      "annualContractValue": 0.0,
      "estimatedMonthlyRevenue": 0.0,
      "contractTerm": 36,
      "contractTermUnit": "Months",
      "contractType": "Per Labor Hour; Mid Month Advance; Deposited Revenue",
      "billingType": "Arrears",
      "district": "D - Boston",
      "region": NaN,
      "siteNumber": "2172"
    }
  }
}